{"type": "node", "id": "29698", "labels": ["assertion"], "properties": {"creation_time": 1512660835838, "event_stamp": "2016-07-25T17:43:06", "last_updated": 1512660835838, "user_id": "usr_579611e01221d", "confidence_level": "100", "truth_value": "positive", "name": "attention is measured by the contrast of Total score in the Montreal Cognitive Assessment", "id": "ass_57964faa36b69", "flag_for_curator": 1, "id_subject_def": "None"}, "PREDICATE": [{"id": "trm_57964b8a66aed"}], "SUBJECT": [{"id": "trm_4a3fd79d09902"}], "PREDICATE_DEF": [{"id": "cnt_57964ea91ff76"}]}