{"type": "node", "id": "28012", "labels": ["assertion"], "properties": {"creation_time": 1512660735495, "event_stamp": "2011-06-23T18:56:09", "last_updated": 1512660735495, "user_id": "usr_4de5345b3b6a8", "confidence_level": "100", "truth_value": "positive", "name": "serial search is measured by the contrast of reaction time of participant minus average reaction time of controls trials in the audio-visual target-detection task", "id": "ass_4e038c49c4bab", "flag_for_curator": 1, "id_subject_def": "NADA"}, "PREDICATE": [{"id": "tsk_4a57abb949889"}], "SUBJECT": [{"id": "trm_4a3fd79d0b0c8"}], "PREDICATE_DEF": [{"id": "cnt_4e038b1c6fd1f"}]}