{"type": "node", "id": "27567", "labels": ["assertion"], "properties": {"creation_time": 1512660706476, "event_stamp": "2011-06-03T17:06:31", "last_updated": 1512660706476, "user_id": "usr_4de5345b3b6a8", "confidence_level": "70", "truth_value": "positive", "name": "memory decay is measured by the contrast of delay minus no delay trials in the delayed nonmatch to sample task", "id": "ass_4de91497a8709", "flag_for_curator": 1, "id_subject_def": "NADA"}, "PREDICATE": [{"id": "tsk_4a57abb9499f1"}], "SUBJECT": [{"id": "trm_4a3fd79d0b92c"}], "PREDICATE_DEF": [{"id": "cnt_4b4a609f11b96"}]}