{"type": "node", "id": "28388", "labels": ["assertion"], "properties": {"creation_time": 1512660754561, "event_stamp": "2012-07-11T17:41:12", "last_updated": 1512660754561, "user_id": "usr_4f177506dde77", "confidence_level": "100", "truth_value": "positive", "name": "auditory perception is measured by the contrast of Interstimulus Interval (ISI) in the auditory temporal discrimination task", "id": "ass_4ffdbab8efbcd", "flag_for_curator": 1, "id_subject_def": "None"}, "PREDICATE": [{"id": "trm_4f240e7f989f8"}], "SUBJECT": [{"id": "trm_4a3fd79d09ab2"}], "PREDICATE_DEF": [{"id": "cnt_4ffdbab8b5539"}]}