{"type": "node", "id": "28027", "labels": ["assertion"], "properties": {"creation_time": 1512660736362, "event_stamp": "2011-06-23T21:59:40", "last_updated": 1512660736362, "user_id": "usr_4de5345b3b6a8", "confidence_level": "100", "truth_value": "positive", "name": "lexical access is measured by the contrast of areas of activation during task minus baseline trials in the Naming (Covert)", "id": "ass_4e03b74c89946", "flag_for_curator": 1, "id_subject_def": "NADA"}, "PREDICATE": [{"id": "trm_4c8990c87035d"}], "SUBJECT": [{"id": "trm_4a3fd79d0b80f"}], "PREDICATE_DEF": [{"id": "cnt_4e03b6ae397cc"}]}