{"type": "node", "id": "28782", "labels": ["assertion"], "properties": {"creation_time": 1512660779784, "event_stamp": "2013-10-15T18:35:34", "last_updated": 1512660779784, "user_id": "usr_51bc76ae9636c", "confidence_level": "100", "truth_value": "positive", "name": "word repetition is measured by the contrast of echolalia in the Autism Diagnostic Interview - Revised", "id": "ass_525d8af6458c4", "flag_for_curator": 1, "id_subject_def": "None"}, "PREDICATE": [{"id": "trm_525d847e2bd0b"}], "SUBJECT": [{"id": "trm_4a3fd79d0b59b"}], "PREDICATE_DEF": [{"id": "cnt_525d8551c4a1a"}]}