{"type": "node", "id": "29331", "labels": ["assertion"], "properties": {"creation_time": 1512660812901, "event_stamp": "2015-09-08T17:13:03", "last_updated": 1512660812901, "user_id": "usr_51bc76ae9636c", "confidence_level": "100", "truth_value": "positive", "name": "reinforcement learning is measured by the contrast of feedback in the deterministic classification", "id": "ass_55ef171f817e8", "flag_for_curator": 1, "id_subject_def": "None"}, "PREDICATE": [{"id": "trm_4e8dd3831f0cc"}], "SUBJECT": [{"id": "trm_557b4993a0fdd"}], "PREDICATE_DEF": [{"id": "cnt_55399dc274d97"}]}