{"type": "node", "id": "27765", "labels": ["assertion"], "properties": {"creation_time": 1512660719245, "event_stamp": "2011-06-13T23:54:53", "last_updated": 1512660719245, "user_id": "usr_4de5345b3b6a8", "confidence_level": "100", "truth_value": "positive", "name": "acoustic phonetic processing is measured by the contrast of accuracy of participant minus average accuracy of controls trials in the Phonological Discrimination", "id": "ass_4df6a34d32a74", "flag_for_curator": 1, "id_subject_def": "NADA"}, "PREDICATE": [{"id": "trm_4c89922cb6402"}], "SUBJECT": [{"id": "trm_4a3fd79d09713"}], "PREDICATE_DEF": [{"id": "cnt_4df6a3169f42a"}]}