{"type": "node", "id": "28881", "labels": ["assertion"], "properties": {"creation_time": 1512660787014, "event_stamp": "2013-10-31T17:09:46", "last_updated": 1512660787014, "user_id": "usr_51bc76ae9636c", "confidence_level": "100", "truth_value": "positive", "name": "naming is measured by the contrast of naming vocabulary in the Differential Ability Scales", "id": "ass_52728eda0f407", "flag_for_curator": 1, "id_subject_def": "None"}, "PREDICATE": [{"id": "trm_5272806688e63"}], "SUBJECT": [{"id": "trm_4a3fd79d0a9dc"}], "PREDICATE_DEF": [{"id": "cnt_527280fcbc7f6"}]}