{"type": "node", "id": "27695", "labels": ["assertion"], "properties": {"creation_time": 1512660714689, "event_stamp": "2011-06-10T16:35:55", "last_updated": 1512660714689, "user_id": "usr_4de5345b3b6a8", "confidence_level": "100", "truth_value": "positive", "name": "lexical access is measured by the contrast of Words - Pseudowords trials in the Lexical decision task", "id": "ass_4df247eb0d903", "flag_for_curator": 1, "id_subject_def": "NADA"}, "PREDICATE": [{"id": "tsk_4a57abb949b38"}], "SUBJECT": [{"id": "trm_4a3fd79d0b80f"}], "PREDICATE_DEF": [{"id": "cnt_4be6ec4cb064c"}]}