{"type": "node", "id": "27591", "labels": ["assertion"], "properties": {"creation_time": 1512660707998, "event_stamp": "2011-06-03T20:11:56", "last_updated": 1512660707998, "user_id": "usr_4de5345b3b6a8", "confidence_level": "70", "truth_value": "positive", "name": "recall is measured by the contrast of visual recognition (doors test) trials in the Doors and People Test", "id": "ass_4de9400cba911", "flag_for_curator": 1, "id_subject_def": "NADA"}, "PREDICATE": [{"id": "tsk_4a57abb949a33"}], "SUBJECT": [{"id": "trm_4a3fd79d0b95b"}], "PREDICATE_DEF": [{"id": "cnt_4de93ddadf379"}]}