{"type": "node", "id": "23956", "labels": ["task"], "properties": {"id_concept_class": "", "creation_time": 1512660590085, "event_stamp": "2012-01-28T15:30:41", "def_id_user": "usr_49a467bf4e0db", "def_event_stamp": "2012-01-28T15:30:41", "last_updated": 1512660590085, "def_id": "def_4f2414a1bb169", "name": "phonetic discrimination task", "alias": "", "definition_text": "A task in which the subject discriminates stimuli based on phonetic features.", "id_user": "usr_49a467bf4e0db", "id": "trm_4f2414a1bab77"}}