{"type": "node", "id": "24367", "labels": ["task"], "properties": {"id_concept_class": "", "creation_time": 1512660601396, "event_stamp": "2017-01-09T18:04:46", "def_id_user": "usr_583366685f18a", "def_event_stamp": "2017-01-09T18:04:46", "last_updated": 1512660601396, "def_id": "def_5873d0be41627", "name": "emotional localizer fMRI task paradigm", "alias": "", "definition_text": "This is an emotional paradigm that include facial judgements of gender, trustworthiness and expression based on face photographs or photographs reduced to the eyes. More precisely, the following conditions were presented:\r\n1 face gender: gender evaluation of the presented human faces;\r\n2 face control: mental assessment on the slope of a gray-scale grid image that may be tilted or not;\r\n3 face trusty: trustworthy evaluation of the presented human faces;\r\n4 expression intention: trustworthy evaluation of the presented human eye images;\r\n5 expression gender: gender evaluation of the presented human eye images;\r\n6 expression control: mental assessment on the slope of a gray-scale grid image that may be tilted or not.", "id_user": "usr_583366685f18a", "id": "trm_5873d0be34b8f"}}