{"type": "node", "id": "23680", "labels": ["task"], "properties": {"id_concept_class": "", "creation_time": 1512660581203, "event_stamp": "2010-09-10T01:33:01", "def_id_user": "usr_4f177506dde77", "def_event_stamp": "2012-08-09T19:11:32", "last_updated": 1512660581203, "def_id": "def_50240b64d2019", "name": "pavlovian conditioning task", "alias": "classical conditioning task", "definition_text": "participants encounter a stimulus (designated the &#34;conditional stimulus&#34; or CS and being one without inherent significance) is paired with an unconditional stimulus or US, so named because it is biologically significant (e.g. food, sex, drug, pain), so that the participant responds to the former in a way that conveys his or her association of the two; subtypes of classical conditioning vary the temporal relationship between the CS and US.", "id_user": "usr_4b9003ea0be96", "id": "trm_4c898acd1f28e"}, "HASCONDITION": [{"id": "con_4de6c84f74297"}, {"id": "con_4de6c8bbe652f"}], "HASCONTRAST": [{"id": "cnt_4de6c84f74508"}, {"id": "cnt_5020421e4a79e"}, {"id": "cnt_4de6c945846f2"}, {"id": "cnt_4de6c9842dbbe"}, {"id": "cnt_5024025b137a6"}, {"id": "cnt_502403657d971"}], "ASSERTS": [{"id": "trm_4a3fd79d098c9"}, {"id": "trm_4a3fd79d0ab70"}, {"id": "trm_4a3fd79d0a637"}, {"id": "trm_4a3fd79d09b28"}, {"id": "trm_502403240a2a2"}], "HASINDICATOR": [{"id": "ind_4de6cae10aad3", "event_stamp": "2011-06-01T23:27:29", "id_user": "usr_4de5345b3b6a8"}, {"id": "ind_4de6caf60c9aa", "event_stamp": "2011-06-01T23:27:50", "id_user": "usr_4de5345b3b6a8"}], "HASCITATION": [{"id": "cit_4de6cb32edf13"}, {"id": "cit_4de6cbabc885d"}, {"id": "cit_4de6cc590c7ea"}, {"id": "cit_4fe8ee5a59c2f"}]}