{"type": "node", "id": "23913", "labels": ["task"], "properties": {"id_concept_class": "", "creation_time": 1512660588892, "event_stamp": "2012-05-21T18:12:10", "def_id_user": "usr_4f177506dde77", "def_event_stamp": "2012-07-18T19:19:40", "last_updated": 1512660588892, "def_id": "def_50070c4cbd651", "name": "immediate memory task", "alias": "IMT", "definition_text": "a number between 2 and 7 digits is displayed for a brief period and is followed briefly by a blank screen, then another number to which participants respond only if it is identical to the first.", "id_user": "usr_49a467bf4e0db", "id": "trm_4fba857ad04ac"}, "HASCONDITION": [{"id": "con_50070cba6b797"}, {"id": "con_50070cd634c82"}, {"id": "con_50070cea20c7b"}], "HASCONTRAST": [{"id": "cnt_50070d3b312f4"}, {"id": "cnt_50070f5d10c03"}], "ASSERTS": [{"id": "trm_50070dce14554"}, {"id": "trm_4a3fd79d09902"}], "HASINDICATOR": [{"id": "ind_50070c5d5af74", "event_stamp": "2012-07-18T19:19:57", "id_user": "usr_4f177506dde77"}]}