{"type": "node", "id": "24133", "labels": ["task"], "properties": {"id_concept_class": "", "creation_time": 1512660595019, "event_stamp": "2013-10-22T18:06:54", "def_id_user": "usr_51bc76ae9636c", "def_event_stamp": "2013-10-22T18:06:54", "last_updated": 1512660595019, "def_id": "def_5266bebe2182a", "name": "Peabody Picture Vocabulary Test", "alias": "PPVT", "definition_text": "The Peabody Picture Vocabulary Test (PPVT) is a vocabulary assessment to assess receptive and expressive vocabulary performance.", "id_user": "usr_51bc76ae9636c", "id": "trm_5266bebe14d2e"}, "HASCONTRAST": [{"id": "cnt_5266c222da58d"}], "ASSERTS": [{"id": "trm_4a3fd79d0b58f"}]}