{"type": "node", "id": "24346", "labels": ["task"], "properties": {"id_concept_class": "", "creation_time": 1512660600703, "event_stamp": "2016-07-27T14:55:28", "def_id_user": "usr_579611e01221d", "def_event_stamp": "2016-07-27T14:55:28", "last_updated": 1512660600703, "def_id": "def_5798cb60410a3", "name": "following commands", "alias": "", "definition_text": "The participant is given verbal instructions such as &#34;make a fist&#34; or &#34;point to the ceiling&#34;. Execution of the command is scored as correct. The commands may be simple or complex (for example having multiple steps).", "id_user": "usr_579611e01221d", "id": "trm_5798cb6027f28"}, "HASCONDITION": [{"id": "con_5798ccf7ef929"}, {"id": "con_5798cd003e9c1"}, {"id": "con_5798cd0763c98"}, {"id": "con_5798cd14446ef"}, {"id": "con_5798cd1c60b32"}], "HASCONTRAST": [{"id": "cnt_5798cd3deaac0"}], "ASSERTS": [{"id": "trm_4a3fd79d0a775"}, {"id": "trm_4a3fd79d0a9a1"}, {"id": "trm_557b4a7315f1b"}], "INBATTERY": [{"id": "tco_5798bc88b2bf2", "event_stamp": "2016-07-27T15:05:15", "id_user": "usr_579611e01221d"}], "HASINDICATOR": [{"id": "ind_5798cce66a95c", "event_stamp": "2016-07-27T15:01:58", "id_user": "usr_579611e01221d"}], "HASIMPLEMENTATION": [{"id": "imp_5798ccd1bd5cc"}]}