{"type": "node", "id": "23947", "labels": ["task"], "properties": {"id_concept_class": "", "creation_time": 1512660589837, "event_stamp": "2012-01-28T15:13:09", "def_id_user": "usr_49a467bf4e0db", "def_event_stamp": "2012-01-28T15:13:09", "last_updated": 1512660589837, "def_id": "def_4f24108555926", "name": "visually guided saccade task", "alias": "", "definition_text": "A task in which subjects make visually guided eye movements.", "id_user": "usr_49a467bf4e0db", "id": "trm_4f24108555294"}, "ASSERTS": [{"id": "trm_4a3fd79d0b4b5"}]}