{"type": "node", "id": "23836", "labels": ["task"], "properties": {"id_concept_class": "", "creation_time": 1512660586676, "event_stamp": "2009-07-10T21:01:20", "def_id_user": "usr_4f177506dde77", "def_event_stamp": "2012-05-16T21:20:31", "last_updated": 1512660586676, "def_id": "def_4fb41a1f53e8a", "name": "word generation task", "alias": "", "definition_text": "Covert: Semantic: subjects listen to or view nouns and silently generate an associated verb, or subjects view a category and silently generate as many exemplars as possible; Orthographic: subjects listen to or view a letter and silently generate as many words as possible that start with that letter; Phonologic: subjects listen to or view a word and silently generate words that rhyme. \r\n\r\nOvert: semantic: subjects listen to or view nouns and overtly generate an associated verb, or subjects view a category and overtly generate as many exemplars as possible; Orthographic: subjects listen to or view a letter and overtly generate as many words as possible that start with that letter; Phonologic: subjects listen to or view a word and overtly generate words that rhyme.", "id_user": "usr_0000000000", "id": "tsk_4a57abb949f3d"}, "HASCONTRAST": [{"id": "cnt_4e022d7430161"}, {"id": "cnt_4e02302350f17"}, {"id": "cnt_4e0232312c822"}], "ASSERTS": [{"id": "trm_4a3fd79d0b87a"}, {"id": "trm_4a3fd79d0b44c"}], "HASINDICATOR": [{"id": "ind_4e022d3e1d312", "event_stamp": "2011-06-22T17:58:22", "id_user": "usr_4de5345b3b6a8"}, {"id": "ind_4e022e8fd2aad", "event_stamp": "2011-06-22T18:03:59", "id_user": "usr_4de5345b3b6a8"}, {"id": "ind_4e02301d96809", "event_stamp": "2011-06-22T18:10:37", "id_user": "usr_4de5345b3b6a8"}, {"id": "ind_4e023223096dc", "event_stamp": "2011-06-22T18:19:15", "id_user": "usr_4de5345b3b6a8"}], "HASCITATION": [{"id": "cit_4e022c2386f8e"}, {"id": "cit_4e022e5d93f39"}]}