{"type": "node", "id": "23789", "labels": ["task"], "properties": {"id_concept_class": "", "creation_time": 1512660585057, "event_stamp": "2009-07-10T21:01:20", "def_id_user": "usr_4de5345b3b6a8", "def_event_stamp": "2011-06-10T21:40:57", "last_updated": 1512660585057, "def_id": "def_4df28f6970e58", "name": "motor sequencing task", "alias": "", "definition_text": "Participants perform several motoric tasks in a specific sequence/order.", "id_user": "usr_0000000000", "id": "tsk_4a57abb949bbf"}, "HASCONTRAST": [{"id": "cnt_4df2917218780"}, {"id": "cnt_4df2918824fb9"}], "ASSERTS": [{"id": "trm_4a3fd79d0addc"}, {"id": "trm_4a3fd79d0a972"}, {"id": "trm_4a3fd79d0b0bd"}], "HASINDICATOR": [{"id": "ind_4df2906823b37", "event_stamp": "2011-06-10T21:45:12", "id_user": "usr_4de5345b3b6a8"}, {"id": "ind_4df2906e41bf8", "event_stamp": "2011-06-10T21:45:18", "id_user": "usr_4de5345b3b6a8"}], "HASCITATION": [{"id": "cit_4df2913e55edf"}, {"id": "cit_4df2914d941c6"}]}