{"type": "node", "id": "25700", "labels": ["concept"], "properties": {"id_concept_class": "", "creation_time": 1512660640829, "event_stamp": "2013-04-01T17:59:46", "def_id_user": "usr_4de5345b3b6a8", "def_event_stamp": "2013-04-01T17:59:46", "last_updated": 1512660640829, "def_id": "def_5159cb12b8961", "name": "reward learning", "alias": "", "definition_text": "A process by which organisms acquire information about stimuli, actions, and contexts that predict positive outcomes, and by which behavior is modified when a novel reward occurs or outcomes are better than expected. Reward learning is a type of reinforcement learning, and similar processes may be involved in learning related to negative reinforcement.", "id_user": "usr_4de5345b3b6a8", "id": "trm_5159cb12a0f92"}, "KINDOF": [{"id": "trm_557b4993a0fdd"}], "HASCITATION": [{"id": "cit_5159cb513591f"}]}