{"type": "node", "id": "25058", "labels": ["concept"], "properties": {"id_concept_class": "ctp_C3", "creation_time": 1512660626063, "event_stamp": "2009-06-22T19:12:54", "def_id_user": "usr_4e42a3196fbcd", "def_event_stamp": "2011-08-10T20:41:26", "last_updated": 1512660626063, "def_id": "def_4e42ecf5ef5a9", "name": "abductive reasoning", "alias": "", "definition_text": "The process of adopting an explanatory hypothesis; inferring the cause A as a possible explanation for the consequence B ", "id_user": "usr_0000000000", "id": "trm_4a3fd79d096be"}, "KINDOF": [{"id": "trm_4a3fd79d0aec1"}], "CLASSIFIEDUNDER": [{"id": "ctp_C3"}]}