{"type": "node", "id": "25652", "labels": ["concept"], "properties": {"id_concept_class": "", "creation_time": 1512660639734, "event_stamp": "2012-06-27T17:37:41", "def_id_user": "usr_4f177506dde77", "def_event_stamp": "2012-06-27T17:37:41", "last_updated": 1512660639734, "def_id": "def_4feb44e5c6c79", "name": "unconscious perception", "alias": "", "definition_text": "the process of perceiving a stimulus without being conscious of having seen it, measurable by electrophysiological response at the time and by recognition testing later", "id_user": "usr_4f177506dde77", "id": "trm_4feb44e5ae25b"}, "KINDOF": [{"id": "trm_4a3fd79d0ab7c"}, {"id": "trm_4a3fd79d0b406"}], "PARTOF": [{"id": "trm_4e89aebaa311d"}, {"id": "trm_5029515e29f7f"}], "HASCITATION": [{"id": "cit_4feb465b90859"}]}