{"type": "node", "id": "25619", "labels": ["concept"], "properties": {"id_concept_class": "", "creation_time": 1512660639008, "event_stamp": "2011-07-28T21:18:28", "def_id_user": "usr_4f39262a2e81e", "def_event_stamp": "2014-01-02T13:52:05", "last_updated": 1512660639008, "def_id": "def_52c56f0534b5e", "name": "crossmodal", "alias": "cross-modal", "definition_text": "A complex of two or more modality-specific [unimodal] stimuli", "id_user": "usr_4e31cbdaeab0d", "id": "trm_4e31d2241319f"}, "HASCITATION": [{"id": "cit_4fa2b55c5b414"}]}