{"type": "node", "id": "25218", "labels": ["concept"], "properties": {"id_concept_class": "ctp_C3", "creation_time": 1512660629621, "event_stamp": "2009-06-22T19:12:55", "def_id_user": "usr_49a467bf4e0db", "def_event_stamp": "2012-03-28T16:51:20", "last_updated": 1512660629621, "def_id": "def_4f7341889a7d1", "name": "divergent thinking", "alias": "", "definition_text": "a thought process or method used to generate creative ideas by exploring many possible solutions.", "id_user": "usr_0000000000", "id": "trm_4a3fd79d0a10a"}, "CLASSIFIEDUNDER": [{"id": "ctp_C3"}]}