{"type": "node", "id": "44640", "labels": ["implementation"], "properties": {"creation_time": 1528248747725, "implementation_name": "Cognition Lab  - NPR", "last_updated": 1528248747725, "implementation_description": "Configurable web-based test paradigm with the digits 1,2,3,4 and adjustable focus (global,local)  and transitions between target and distractor to study negative priming effects", "name": "Cognition Lab  - NPR", "id": "imp_KgnfCtJRzA4Lw", "implementation_uri": "https://cognitionlab.com/portfolio/negative-priming/gallery/library/"}}