{"type": "node", "id": "29976", "labels": ["disorder"], "properties": {"event_stamp": "2013-11-20T15:38:34", "id_protocol": "DOID", "name": "adjustment disorder", "definition": "A disease of mental health that is an abnormal and excessive emotional and behavioral reaction to a life stress that develops within 3 months of a life stress, and which is stronger or greater than what would be expected for the type of event that occurred.", "id_user": "usr_52a0cf72ed5c5", "id": "dso_507", "flag_for_curator": 1}}