{"type": "node", "id": "30931", "labels": ["citation"], "properties": {"citation_pubname": "Brain research (Brain Res)", "event_stamp": "2011-07-28T22:18:51", "citation_pmid": "16876772", "citation_desc": "Audiovisual synchrony perception for music, speech, and object actions.", "citation_type": "CT2", "citation_url": "http://www.ncbi.nlm.nih.gov/entrez/eutils/elink.fcgi?dbfrom=pubmed&id=16876772&retmode=ref&cmd=prlinks", "citation_comment": "Via PubMed API", "id_user": "usr_4e31cbdaeab0d", "id": "cit_4e31e04b44751", "citation_source": "PubMed API", "citation_authors": "Vatakis A, Spence C", "citation_pubdate": "2006 Sep 21"}}