{"type": "node", "id": "31056", "labels": ["citation"], "properties": {"event_stamp": "2012-07-18T22:16:09", "citation_pubname": "Brain : a journal of neurology (Brain)", "citation_pmid": "16520329", "citation_desc": "Functional connectivity of the fusiform gyrus during a face-matching task in subjects with mild cognitive impairment.", "citation_url": "http://www.ncbi.nlm.nih.gov/entrez/eutils/elink.fcgi?dbfrom=pubmed&id=16520329&retmode=ref&cmd=prlinks", "citation_type": "CT2", "citation_comment": "Via PubMed API", "id_user": "usr_4f177506dde77", "id": "cit_500735a9bce25", "citation_source": "PubMed API", "citation_authors": "Bokde AL, Lopez-Bayo P, Meindl T, Pechler S, Born C, Faltraco F, Teipel SJ, M\u00c3\u00b6ller HJ, Hampel H", "citation_pubdate": "2006 May"}}