{"type": "node", "id": "31340", "labels": ["citation"], "properties": {"event_stamp": "2013-01-28T22:26:21", "citation_pubname": "Schizophrenia research (Schizophr Res)", "citation_pmid": "21764563", "citation_desc": "Remission and recovery during the first outpatient year of the early course of schizophrenia.", "citation_type": "CT2", "citation_url": "http://www.ncbi.nlm.nih.gov/entrez/eutils/elink.fcgi?dbfrom=pubmed&id=21764563&retmode=ref&cmd=prlinks", "citation_comment": "", "id_user": "usr_4de5345b3b6a8", "id": "cit_5106fb0dd9b6b", "citation_source": "PubMed API", "citation_authors": "Ventura J, Subotnik KL, Guzik LH, Hellemann GS, Gitlin MJ, Wood RC, Nuechterlein KH", "citation_pubdate": "2011 Oct"}}