{"type": "node", "id": "30504", "labels": ["citation"], "properties": {"citation_pubname": " (J Neurosci)", "event_stamp": "2011-05-23T20:59:41", "citation_pmid": "11459880", "citation_desc": "Anticipation of increasing monetary reward selectively recruits nucleus accumbens.", "citation_url": "http://www.ncbi.nlm.nih.gov/entrez/eutils/elink.fcgi?dbfrom=pubmed&id=11459880&retmode=ref&cmd=prlinks", "citation_type": "CT2", "citation_comment": "Via PubMed API", "id_user": "usr_4da607a02849b", "id": "cit_4ddacabd42138", "citation_source": "PubMed API", "citation_authors": "Knutson B, Adams CM, Fong GW, Hommer D", "citation_pubdate": "2001 Aug 15"}}