{"type": "node", "id": "31494", "labels": ["citation"], "properties": {"event_stamp": "2015-04-21T22:55:45", "citation_pubname": "Psychopathology (Psychopathology)", "citation_pmid": "24192559", "citation_desc": "Susceptibility to distraction by social cues in borderline personality disorder.", "citation_type": "CT2", "citation_url": "http://www.ncbi.nlm.nih.gov/entrez/eutils/elink.fcgi?dbfrom=pubmed&id=24192559&retmode=ref&cmd=prlinks", "citation_comment": "", "id_user": "usr_4e42a3196fbcd", "id": "cit_5536d57125154", "citation_source": "PubMed API", "citation_authors": "Krause-Utz A, Elzinga BM, Oei NY, Spinhoven P, Bohus M, Schmahl C", "citation_pubdate": "2014"}}