{"type": "node", "id": "31263", "labels": ["citation"], "properties": {"event_stamp": "2013-01-16T23:06:30", "citation_pubname": "Psychopharmacology (Psychopharmacology (Berl))", "citation_pmid": "21086119", "citation_desc": "A computer-automated touchscreen paired-associates learning (PAL) task for mice: impairments following administration of scopolamine or dicyclomine and improvements following donepezil.", "citation_type": "CT2", "citation_url": "http://www.ncbi.nlm.nih.gov/entrez/eutils/elink.fcgi?dbfrom=pubmed&id=21086119&retmode=ref&cmd=prlinks", "citation_comment": "", "id_user": "usr_4de5345b3b6a8", "id": "cit_50f7327662500", "citation_source": "PubMed API", "citation_authors": "Bartko SJ, Vendrell I, Saksida LM, Bussey TJ", "citation_pubdate": "2011 Mar"}}