{"type": "node", "id": "31533", "labels": ["citation"], "properties": {"event_stamp": "2015-04-28T18:50:22", "citation_pubname": "Proceedings of the National Academy of Sciences of the United States of America (Proc Natl Acad Sci U S A)", "citation_pmid": "24550270", "citation_desc": "Predicting risky choices from brain activity patterns.", "citation_type": "CT2", "citation_url": "http://www.ncbi.nlm.nih.gov/entrez/eutils/elink.fcgi?dbfrom=pubmed&id=24550270&retmode=ref&cmd=prlinks", "citation_comment": "", "id_user": "usr_51bc76ae9636c", "id": "cit_553fd66e39d56", "citation_source": "PubMed API", "citation_authors": "Helfinstein SM, Schonberg T, Congdon E, Karlsgodt KH, Mumford JA, Sabb FW, Cannon TD, London ED, Bilder RM, Poldrack RA", "citation_pubdate": "2014 Feb 18"}}