{"type": "node", "id": "30468", "labels": ["citation"], "properties": {"event_stamp": "2011-02-11T20:39:56", "citation_pubname": "Psychological science : a journal of the American Psychological Society / APS (Psychol Sci)", "citation_pmid": "19152538", "citation_desc": "Tonic activity level in the right prefrontal cortex predicts individuals&#39; risk taking.", "citation_url": "http://www.ncbi.nlm.nih.gov/entrez/eutils/elink.fcgi?dbfrom=pubmed&id=19152538&retmode=ref&cmd=prlinks", "citation_type": "CT2", "citation_comment": "Via PubMed API", "id_user": "usr_4ac2cdeede9e6", "id": "cit_4d559e9ca6aaf", "citation_source": "PubMed API", "citation_authors": "Gianotti LR, Knoch D, Faber PL, Lehmann D, Pascual-Marqui RD, Diezi C, Schoch C, Eisenegger C, Fehr E", "citation_pubdate": "2009 Jan"}}