{"type": "node", "id": "30850", "labels": ["citation"], "properties": {"event_stamp": "2011-06-21T17:33:02", "citation_pubname": "Cyberpsychology & behavior : the impact of the Internet, multimedia and virtual reality on behavior and society (Cyberpsychol Behav)", "citation_pmid": "19025464", "citation_desc": "Experimental evidence for suspense as determinant of video game enjoyment.", "citation_url": "http://www.ncbi.nlm.nih.gov/entrez/eutils/elink.fcgi?dbfrom=pubmed&id=19025464&retmode=ref&cmd=prlinks", "citation_type": "CT2", "citation_comment": "Via PubMed API", "id_user": "usr_4de5345b3b6a8", "id": "cit_4e00d5ce35eca", "citation_source": "PubMed API", "citation_authors": "Klimmt C, Rizzo A, Vorderer P, Koch J, Fischer T", "citation_pubdate": "2009 Feb"}}