{"type": "node", "id": "31358", "labels": ["citation"], "properties": {"event_stamp": "2013-03-28T18:54:39", "citation_pubname": "Acta psychologica (Acta Psychol (Amst))", "citation_pmid": "23333876", "citation_desc": "Semantic consistency versus perceptual salience in visual scenes: findings from change detection.", "citation_type": "CT2", "citation_url": "http://www.ncbi.nlm.nih.gov/entrez/eutils/elink.fcgi?dbfrom=pubmed&id=23333876&retmode=ref&cmd=prlinks", "citation_comment": "", "id_user": "usr_4de5345b3b6a8", "id": "cit_515491ef81fe5", "citation_source": "PubMed API", "citation_authors": "Spotorno S, Tatler BW, Faure S", "citation_pubdate": "2013 Feb"}}