{"type": "node", "id": "30841", "labels": ["citation"], "properties": {"event_stamp": "2011-06-20T23:20:15", "citation_pubname": "Neuropsychology (Neuropsychology)", "citation_pmid": "17402826", "citation_desc": "Neuropsychological functioning of girls with attention-deficit/hyperactivity disorder followed prospectively into adolescence: evidence for continuing deficits?", "citation_url": "http://www.ncbi.nlm.nih.gov/entrez/eutils/elink.fcgi?dbfrom=pubmed&id=17402826&retmode=ref&cmd=prlinks", "citation_type": "CT2", "citation_comment": "Via PubMed API", "id_user": "usr_4de5345b3b6a8", "id": "cit_4dffd5afb9aab", "citation_source": "PubMed API", "citation_authors": "Hinshaw SP, Carte ET, Fan C, Jassy JS, Owens EB", "citation_pubdate": "2007 Mar"}}