{"type": "node", "id": "56781", "labels": ["citation"], "properties": {"creation_time": 1581677354632, "citation_pmid": "", "last_updated": 1581677354632, "citation_desc": "Visual perception of biological motion and a model for its analysis", "citation_type": "", "citation_url": "http://link.springer.com/10.3758/BF03212378", "citation_comment": "", "citation_authors": "Gunnar Johansson", "citation_pubdate": "1973-06-01", "citation_pubname": "Perception & Psychophysics", "name": "Visual perception of biological motion and a model for its analysis", "id": "cit_zv0Do1ZKxMq0S", "citation_source": "", "doi": "10.3758/BF03212378"}}