{"type": "node", "id": "31085", "labels": ["citation"], "properties": {"citation_pubname": " (Brain Res Brain Res Rev)", "event_stamp": "2012-07-23T23:12:10", "citation_pmid": "11516773", "citation_desc": "Applications of the Morris water maze in the study of learning and memory.", "citation_url": "http://www.ncbi.nlm.nih.gov/entrez/eutils/elink.fcgi?dbfrom=pubmed&id=11516773&retmode=ref&cmd=prlinks", "citation_type": "CT2", "citation_comment": "Via PubMed API", "id_user": "usr_4f177506dde77", "id": "cit_500dda4a12ac1", "citation_source": "PubMed API", "citation_authors": "D&#39;Hooge R, De Deyn PP", "citation_pubdate": "2001 Aug"}}