{"type": "node", "id": "31073", "labels": ["citation"], "properties": {"citation_pubname": " (Psychophysiology)", "event_stamp": "2012-07-23T19:37:09", "citation_pmid": "10934914", "citation_desc": "Memory for drawings in locations: spatial source memory and event-related potentials.", "citation_url": "http://www.ncbi.nlm.nih.gov/entrez/eutils/elink.fcgi?dbfrom=pubmed&id=10934914&retmode=ref&cmd=prlinks", "citation_type": "CT2", "citation_comment": "Via PubMed API", "id_user": "usr_4f177506dde77", "id": "cit_500da7e5aea97", "citation_source": "PubMed API", "citation_authors": "Van Petten C, Senkfor AJ, Newberg WM", "citation_pubdate": "2000 Jul"}}